{
  "generatedAt": "2026-06-25T16:26:26.572Z",
  "target": {
    "province": "陕西",
    "subject": "物理类",
    "score": 662,
    "rank": 1558
  },
  "rules": {
    "scoreRange": "630-679",
    "include": "985/C9 且匹配计算机、软件、AI、电子信息、通信、自动化、电气、集成电路、智能制造、航空航天等工科主线",
    "exclude": "医学/医工/医疗、专项、强基、综评、中外合作/合作办学、卓越优才、高收费、预科、港校/港澳台合作",
    "matching": "优先以2026招生计划专业为主键反查2025同名专业；无同名时标注近似专业；仍无匹配则提示2025待核。"
  },
  "summary": {
    "total": 64,
    "focusItems": 21,
    "ordinaryMajorItems": 64,
    "coverageAuditItems": 0,
    "closeItems": 24,
    "sprintItems": 12,
    "stableItems": 28
  },
  "focus": [
    {
      "schoolKey": "hit",
      "school": "哈尔滨工业大学",
      "priority": 1,
      "conclusion": "哈工大本部普通批平台最强，但当前库内2025陕西物理普通类最低线索为未来技术拔尖班679，比662高17分。结论是保留第一优先咨询和极高冲刺，不进入稳妥层。",
      "items": [
        {
          "schoolKey": "hit",
          "school": "哈尔滨工业大学",
          "shortName": "哈工大本部",
          "city": "哈尔滨",
          "tier": "985/C9/211/双一流",
          "major": "工科试验班（未来技术拔尖班）",
          "minScore": 679,
          "maxScore": 682,
          "avgScore": 680.3,
          "rank": 0,
          "plan": 0,
          "planYear": 2026,
          "scoreGap": 17,
          "rankGap": -1558,
          "band": "极高冲刺",
          "track": "未来技术/强工科/哈工大本部",
          "recommendation": "极高冲刺",
          "expertScore": 82,
          "sourceLevel": "A",
          "admissionCategory": "普通类",
          "isCoverageAudit": false,
          "notes": "哈工大官方录取分数接口：2025陕西校本部物理+化学普通类，未来技术拔尖班最低679；校本部普通物理类最低679、平均681.5、最高687。640-660按普通批本部基本不匹配，只作高分冲刺和校方咨询参考。",
          "planMatchType": "2025候选基线",
          "matched2025Major": "工科试验班（未来技术拔尖班）",
          "riskTags": [
            "大类分流/专业清待核"
          ],
          "priorityGroups": [
            "C9",
            "国防七子"
          ],
          "focusOrder": 1,
          "action": "只留极高冲刺和招生办咨询，不能当稳项。"
        }
      ]
    },
    {
      "schoolKey": "xjtu",
      "school": "西安交通大学",
      "priority": 2,
      "conclusion": "西交大是当前最值得深入拆解的本地C9。软件工程660、智能感知与仪器660贴线，智慧能源653、智能过程655、智能制造/航天航空649更有缓冲；核心风险在专业组、二次分流、调剂和软件收费。",
      "items": [
        {
          "schoolKey": "xjtu",
          "school": "西安交通大学",
          "shortName": "西交大",
          "city": "西安",
          "tier": "985/C9/双一流",
          "major": "具身智能",
          "minScore": 678,
          "avgScore": 680,
          "maxScore": 682,
          "rank": 536,
          "maxRank": 392,
          "plan": 9,
          "planYear": 2026,
          "scoreGap": 16,
          "rankGap": -1022,
          "band": "极高冲刺",
          "track": "计算机/软件/AI/数据/网安",
          "recommendation": "极高冲刺",
          "expertScore": 107,
          "sourceLevel": "A",
          "admissionCategory": "普通类",
          "isCoverageAudit": false,
          "notes": "2026计划专业；2025近似匹配：人工智能（新工科卓越计划），最低678、平均680、最高682。",
          "planMatchType": "近似匹配",
          "matched2025Major": "人工智能（新工科卓越计划）",
          "riskTags": [
            "2025近似专业"
          ],
          "priorityGroups": [
            "C9"
          ],
          "focusOrder": 2
        },
        {
          "schoolKey": "xjtu",
          "school": "西安交通大学",
          "shortName": "西交大",
          "city": "西安",
          "tier": "985/C9/双一流",
          "major": "人工智能（新工科卓越计划）",
          "minScore": 678,
          "avgScore": 680,
          "maxScore": 682,
          "rank": 536,
          "maxRank": 392,
          "plan": 4,
          "planYear": 2026,
          "scoreGap": 16,
          "rankGap": -1022,
          "band": "极高冲刺",
          "track": "计算机/软件/AI/数据/网安",
          "recommendation": "极高冲刺",
          "expertScore": 107,
          "sourceLevel": "A",
          "admissionCategory": "普通类",
          "isCoverageAudit": false,
          "notes": "2026计划专业；2025同名匹配：人工智能（新工科卓越计划），最低678、平均680、最高682。",
          "planMatchType": "同名匹配",
          "matched2025Major": "人工智能（新工科卓越计划）",
          "riskTags": [],
          "priorityGroups": [
            "C9"
          ],
          "focusOrder": 2
        },
        {
          "schoolKey": "xjtu",
          "school": "西安交通大学",
          "shortName": "西交大",
          "city": "西安",
          "tier": "985/C9/双一流",
          "major": "电子科学与技术",
          "minScore": 663,
          "avgScore": 665,
          "maxScore": 669,
          "rank": 1379,
          "maxRank": 993,
          "plan": 36,
          "planYear": 2026,
          "scoreGap": 1,
          "rankGap": -179,
          "band": "冲刺",
          "track": "电子信息/通信/集成电路/电气",
          "recommendation": "冲刺",
          "expertScore": 0,
          "sourceLevel": "A",
          "admissionCategory": "普通类",
          "isCoverageAudit": false,
          "notes": "2026计划专业；2025同名匹配：电子科学与技术，最低663、平均665、最高669。",
          "planMatchType": "同名匹配",
          "matched2025Major": "电子科学与技术",
          "riskTags": [],
          "priorityGroups": [
            "C9"
          ],
          "focusOrder": 2
        },
        {
          "schoolKey": "xjtu",
          "school": "西安交通大学",
          "shortName": "西交大",
          "city": "西安",
          "tier": "985/C9/双一流",
          "major": "微电子科学与工程",
          "minScore": 665,
          "avgScore": 666,
          "maxScore": 673,
          "rank": 1240,
          "maxRank": 771,
          "plan": 48,
          "planYear": 2026,
          "scoreGap": 3,
          "rankGap": -318,
          "band": "冲刺",
          "track": "电子信息/通信/集成电路/电气",
          "recommendation": "冲刺",
          "expertScore": 113,
          "sourceLevel": "A",
          "admissionCategory": "普通类",
          "isCoverageAudit": false,
          "notes": "2026计划专业；2025同名匹配：微电子科学与工程，最低665、平均666、最高673。",
          "planMatchType": "同名匹配",
          "matched2025Major": "微电子科学与工程",
          "riskTags": [],
          "priorityGroups": [
            "C9"
          ],
          "focusOrder": 2
        },
        {
          "schoolKey": "xjtu",
          "school": "西安交通大学",
          "shortName": "西交大",
          "city": "西安",
          "tier": "985/C9/双一流",
          "major": "工科试验班（计算机科学技术类）",
          "minScore": 666,
          "avgScore": 668,
          "maxScore": 673,
          "rank": 1165,
          "maxRank": 771,
          "plan": 27,
          "planYear": 2026,
          "scoreGap": 4,
          "rankGap": -393,
          "band": "冲刺",
          "track": "计算机/软件/AI/数据/网安",
          "recommendation": "冲刺",
          "expertScore": 111,
          "sourceLevel": "A",
          "admissionCategory": "普通类",
          "isCoverageAudit": false,
          "notes": "2026计划专业；2025同名匹配：工科试验班（计算机科学技术类），最低666、平均668、最高673。",
          "planMatchType": "同名匹配",
          "matched2025Major": "工科试验班（计算机科学技术类）",
          "riskTags": [],
          "priorityGroups": [
            "C9"
          ],
          "focusOrder": 2
        },
        {
          "schoolKey": "xjtu",
          "school": "西安交通大学",
          "shortName": "西交大",
          "city": "西安",
          "tier": "985/C9/双一流",
          "major": "工科试验班（材料创新设计与智能制备国卓班）",
          "minScore": 666,
          "avgScore": 668,
          "maxScore": 674,
          "rank": 1165,
          "maxRank": 708,
          "plan": 4,
          "planYear": 2026,
          "scoreGap": 4,
          "rankGap": -393,
          "band": "冲刺",
          "track": "工科方向待核",
          "recommendation": "冲刺",
          "expertScore": 0,
          "sourceLevel": "A",
          "admissionCategory": "普通类",
          "isCoverageAudit": false,
          "notes": "2026计划专业；2025同名匹配：工科试验班（材料创新设计与智能制备国卓班），最低666、平均668、最高674。",
          "planMatchType": "同名匹配",
          "matched2025Major": "工科试验班（材料创新设计与智能制备国卓班）",
          "riskTags": [],
          "priorityGroups": [
            "C9"
          ],
          "focusOrder": 2
        },
        {
          "schoolKey": "xjtu",
          "school": "西安交通大学",
          "shortName": "西交大",
          "city": "西安",
          "tier": "985/C9/双一流",
          "major": "自动化",
          "minScore": 667,
          "avgScore": 669,
          "maxScore": 678,
          "rank": 1103,
          "maxRank": 536,
          "plan": 44,
          "planYear": 2026,
          "scoreGap": 5,
          "rankGap": -455,
          "band": "冲刺",
          "track": "自动化/机器人/智能制造/测控",
          "recommendation": "冲刺",
          "expertScore": 111,
          "sourceLevel": "A",
          "admissionCategory": "普通类",
          "isCoverageAudit": false,
          "notes": "2026计划专业；2025同名匹配：自动化，最低667、平均669、最高678。",
          "planMatchType": "同名匹配",
          "matched2025Major": "自动化",
          "riskTags": [],
          "priorityGroups": [
            "C9"
          ],
          "focusOrder": 2
        },
        {
          "schoolKey": "xjtu",
          "school": "西安交通大学",
          "shortName": "西交大",
          "city": "西安",
          "tier": "985/C9/双一流",
          "major": "电气工程及其自动化（智能电气领军班）",
          "minScore": 670,
          "avgScore": 673,
          "maxScore": 676,
          "rank": 932,
          "maxRank": 619,
          "plan": 81,
          "planYear": 2026,
          "scoreGap": 8,
          "rankGap": -626,
          "band": "冲刺",
          "track": "电子信息/通信/集成电路/电气",
          "recommendation": "冲刺",
          "expertScore": 0,
          "sourceLevel": "A",
          "admissionCategory": "普通类",
          "isCoverageAudit": false,
          "notes": "2026计划专业；2025近似匹配：工科试验班（电气类），最低670、平均673、最高676。",
          "planMatchType": "近似匹配",
          "matched2025Major": "工科试验班（电气类）",
          "riskTags": [
            "2025近似专业"
          ],
          "priorityGroups": [
            "C9"
          ],
          "focusOrder": 2
        },
        {
          "schoolKey": "xjtu",
          "school": "西安交通大学",
          "shortName": "西交大",
          "city": "西安",
          "tier": "985/C9/双一流",
          "major": "工科试验班（智能感知与仪器国卓班）",
          "minScore": 671,
          "avgScore": 674,
          "maxScore": 680,
          "rank": 882,
          "maxRank": 460,
          "plan": 5,
          "planYear": 2026,
          "scoreGap": 9,
          "rankGap": -676,
          "band": "冲刺",
          "track": "自动化/机器人/智能制造/测控",
          "recommendation": "冲刺",
          "expertScore": 0,
          "sourceLevel": "A",
          "admissionCategory": "普通类",
          "isCoverageAudit": false,
          "notes": "2026计划专业；2025同名匹配：工科试验班（智能感知与仪器国卓班），最低671、平均674、最高680。",
          "planMatchType": "同名匹配",
          "matched2025Major": "工科试验班（智能感知与仪器国卓班）",
          "riskTags": [],
          "priorityGroups": [
            "C9"
          ],
          "focusOrder": 2
        },
        {
          "schoolKey": "xjtu",
          "school": "西安交通大学",
          "shortName": "西交大",
          "city": "西安",
          "tier": "985/C9/双一流",
          "major": "信息工程",
          "minScore": 662,
          "avgScore": 663,
          "maxScore": 667,
          "rank": 1456,
          "maxRank": 1103,
          "plan": 44,
          "planYear": 2026,
          "scoreGap": 0,
          "rankGap": -102,
          "band": "贴线核心",
          "track": "电子信息/通信/集成电路/电气",
          "recommendation": "高优先",
          "expertScore": 117,
          "sourceLevel": "A",
          "admissionCategory": "普通类",
          "isCoverageAudit": false,
          "notes": "2026计划专业；2025同名匹配：信息工程，最低662、平均663、最高667。",
          "planMatchType": "同名匹配",
          "matched2025Major": "信息工程",
          "riskTags": [],
          "priorityGroups": [
            "C9"
          ],
          "focusOrder": 2
        },
        {
          "schoolKey": "xjtu",
          "school": "西安交通大学",
          "shortName": "西交大",
          "city": "西安",
          "tier": "985/C9/双一流",
          "major": "软件工程",
          "minScore": 660,
          "avgScore": 662,
          "maxScore": 666,
          "rank": 1626,
          "maxRank": 1165,
          "plan": 27,
          "planYear": 2026,
          "scoreGap": -2,
          "rankGap": 68,
          "band": "贴线核心",
          "track": "计算机/软件/AI/数据/网安",
          "recommendation": "高优先",
          "expertScore": 118,
          "sourceLevel": "A",
          "admissionCategory": "普通类",
          "isCoverageAudit": false,
          "notes": "2026计划专业；2025同名匹配：软件工程，最低660、平均662、最高666。",
          "planMatchType": "同名匹配",
          "matched2025Major": "软件工程",
          "riskTags": [],
          "priorityGroups": [
            "C9"
          ],
          "focusOrder": 2
        },
        {
          "schoolKey": "xjtu",
          "school": "西安交通大学",
          "shortName": "西交大",
          "city": "西安",
          "tier": "985/C9/双一流",
          "major": "工科试验班（智能感知与仪器）",
          "minScore": 660,
          "avgScore": 661,
          "maxScore": 663,
          "rank": 1626,
          "maxRank": 1379,
          "plan": 6,
          "planYear": 2026,
          "scoreGap": -2,
          "rankGap": 68,
          "band": "贴线核心",
          "track": "自动化/机器人/智能制造/测控",
          "recommendation": "高优先",
          "expertScore": 110,
          "sourceLevel": "A",
          "admissionCategory": "普通类",
          "isCoverageAudit": false,
          "notes": "2026计划专业；2025同名匹配：工科试验班（智能感知与仪器），最低660、平均661、最高663。",
          "planMatchType": "同名匹配",
          "matched2025Major": "工科试验班（智能感知与仪器）",
          "riskTags": [],
          "priorityGroups": [
            "C9"
          ],
          "focusOrder": 2
        },
        {
          "schoolKey": "xjtu",
          "school": "西安交通大学",
          "shortName": "西交大",
          "city": "西安",
          "tier": "985/C9/双一流",
          "major": "工科试验班（材料创新设计与智能制备）",
          "minScore": 658,
          "avgScore": 660,
          "maxScore": 663,
          "rank": 1794,
          "maxRank": 1379,
          "plan": 6,
          "planYear": 2026,
          "scoreGap": -4,
          "rankGap": 236,
          "band": "冲稳",
          "track": "工科方向待核",
          "recommendation": "高优先",
          "expertScore": 0,
          "sourceLevel": "A",
          "admissionCategory": "普通类",
          "isCoverageAudit": false,
          "notes": "2026计划专业；2025同名匹配：工科试验班（材料创新设计与智能制备），最低658、平均660、最高663。",
          "planMatchType": "同名匹配",
          "matched2025Major": "工科试验班（材料创新设计与智能制备）",
          "riskTags": [],
          "priorityGroups": [
            "C9"
          ],
          "focusOrder": 2
        },
        {
          "schoolKey": "xjtu",
          "school": "西安交通大学",
          "shortName": "西交大",
          "city": "西安",
          "tier": "985/C9/双一流",
          "major": "工科试验班（智能过程与装备国卓班）",
          "minScore": 655,
          "avgScore": 657,
          "maxScore": 660,
          "rank": 2051,
          "maxRank": 1626,
          "plan": 4,
          "planYear": 2026,
          "scoreGap": -7,
          "rankGap": 493,
          "band": "冲稳",
          "track": "工科方向待核",
          "recommendation": "高优先",
          "expertScore": 111,
          "sourceLevel": "A",
          "admissionCategory": "普通类",
          "isCoverageAudit": false,
          "notes": "2026计划专业；2025同名匹配：工科试验班（智能过程与装备国卓班），最低655、平均657、最高660。",
          "planMatchType": "同名匹配",
          "matched2025Major": "工科试验班（智能过程与装备国卓班）",
          "riskTags": [],
          "priorityGroups": [
            "C9"
          ],
          "focusOrder": 2
        },
        {
          "schoolKey": "xjtu",
          "school": "西安交通大学",
          "shortName": "西交大",
          "city": "西安",
          "tier": "985/C9/双一流",
          "major": "工科试验班（智慧能源领军班）",
          "minScore": 653,
          "avgScore": 658,
          "maxScore": 673,
          "rank": 2246,
          "maxRank": 771,
          "plan": 195,
          "planYear": 2026,
          "scoreGap": -9,
          "rankGap": 688,
          "band": "冲稳",
          "track": "能源/电气",
          "recommendation": "高优先",
          "expertScore": 0,
          "sourceLevel": "A",
          "admissionCategory": "普通类",
          "isCoverageAudit": false,
          "notes": "2026计划专业；2025近似匹配：工科试验班（智慧能源类），最低653、平均658、最高673。",
          "planMatchType": "近似匹配",
          "matched2025Major": "工科试验班（智慧能源类）",
          "riskTags": [
            "2025近似专业"
          ],
          "priorityGroups": [
            "C9"
          ],
          "focusOrder": 2
        },
        {
          "schoolKey": "xjtu",
          "school": "西安交通大学",
          "shortName": "西交大",
          "city": "西安",
          "tier": "985/C9/双一流",
          "major": "工科试验班（智慧能源国卓班）",
          "minScore": 653,
          "avgScore": 658,
          "maxScore": 673,
          "rank": 2246,
          "maxRank": 771,
          "plan": 7,
          "planYear": 2026,
          "scoreGap": -9,
          "rankGap": 688,
          "band": "冲稳",
          "track": "能源/电气",
          "recommendation": "高优先",
          "expertScore": 0,
          "sourceLevel": "A",
          "admissionCategory": "普通类",
          "isCoverageAudit": false,
          "notes": "2026计划专业；2025近似匹配：工科试验班（智慧能源类），最低653、平均658、最高673。",
          "planMatchType": "近似匹配",
          "matched2025Major": "工科试验班（智慧能源类）",
          "riskTags": [
            "2025近似专业"
          ],
          "priorityGroups": [
            "C9"
          ],
          "focusOrder": 2
        },
        {
          "schoolKey": "xjtu",
          "school": "西安交通大学",
          "shortName": "西交大",
          "city": "西安",
          "tier": "985/C9/双一流",
          "major": "工科试验班（航天航空领军班）",
          "minScore": 649,
          "avgScore": 654,
          "maxScore": 661,
          "rank": 2630,
          "maxRank": 1544,
          "plan": 27,
          "planYear": 2026,
          "scoreGap": -13,
          "rankGap": 1072,
          "band": "稳妥",
          "track": "低空/航空航天/无人系统",
          "recommendation": "高优先",
          "expertScore": 0,
          "sourceLevel": "A",
          "admissionCategory": "普通类",
          "isCoverageAudit": false,
          "notes": "2026计划专业；2025近似匹配：工科试验班（航天航空类），最低649、平均654、最高661。",
          "planMatchType": "近似匹配",
          "matched2025Major": "工科试验班（航天航空类）",
          "riskTags": [
            "2025近似专业"
          ],
          "priorityGroups": [
            "C9"
          ],
          "focusOrder": 2
        },
        {
          "schoolKey": "xjtu",
          "school": "西安交通大学",
          "shortName": "西交大",
          "city": "西安",
          "tier": "985/C9/双一流",
          "major": "工科试验班（智能制造领军班）",
          "minScore": 649,
          "avgScore": 655,
          "maxScore": 668,
          "rank": 2630,
          "maxRank": 1043,
          "plan": 104,
          "planYear": 2026,
          "scoreGap": -13,
          "rankGap": 1072,
          "band": "稳妥",
          "track": "自动化/机器人/智能制造/测控",
          "recommendation": "高优先",
          "expertScore": 0,
          "sourceLevel": "A",
          "admissionCategory": "普通类",
          "isCoverageAudit": false,
          "notes": "2026计划专业；2025近似匹配：工科试验班（智能制造类），最低649、平均655、最高668。",
          "planMatchType": "近似匹配",
          "matched2025Major": "工科试验班（智能制造类）",
          "riskTags": [
            "2025近似专业"
          ],
          "priorityGroups": [
            "C9"
          ],
          "focusOrder": 2
        }
      ]
    },
    {
      "schoolKey": "hitwh",
      "school": "哈尔滨工业大学（威海）",
      "priority": 3,
      "conclusion": "哈工大威海当前保留非卓越优才的普通类近分方向；带卓越优才字样的项目先按特殊类型风险屏蔽，只有招生办明确普通批可报后再单独加回。",
      "items": [
        {
          "schoolKey": "hitwh",
          "school": "哈尔滨工业大学（威海）",
          "shortName": "哈工大威海",
          "city": "威海/哈尔滨",
          "tier": "985/C9/211/双一流",
          "major": "工科试验班（机器人与智能装备拔尖班）",
          "minScore": 650,
          "maxScore": 0,
          "avgScore": 0,
          "rank": 2629,
          "plan": 0,
          "planYear": 2026,
          "scoreGap": -12,
          "rankGap": 1071,
          "band": "稳妥",
          "track": "自动化/机器人/智能制造/测控",
          "recommendation": "高优先",
          "expertScore": 106,
          "sourceLevel": "B",
          "admissionCategory": "普通类",
          "isCoverageAudit": false,
          "notes": "当前库仅有2025最低分，平均分/最高分缺失，需补哈工大威海官方或省考试院分专业录取明细；本专业类内任选专业；EOL备注为前2年威海校区、后2年校本部，需以2026章程和招生办答复复核。",
          "planMatchType": "2025候选基线",
          "matched2025Major": "工科试验班（机器人与智能装备拔尖班）",
          "riskTags": [
            "大类分流/专业清待核"
          ],
          "priorityGroups": [
            "C9",
            "国防七子"
          ],
          "focusOrder": 3,
          "action": "强校异地校区重点关注，先核普通批可报专业、校区安排、毕业证和转专业。"
        },
        {
          "schoolKey": "hitwh",
          "school": "哈尔滨工业大学（威海）",
          "shortName": "哈工大威海",
          "city": "威海/哈尔滨",
          "tier": "985/C9/211/双一流",
          "major": "工科试验班（AI加先进技术领军班）",
          "minScore": 644,
          "maxScore": 0,
          "avgScore": 0,
          "rank": 3291,
          "plan": 0,
          "planYear": 2026,
          "scoreGap": -18,
          "rankGap": 1733,
          "band": "稳妥",
          "track": "计算机/软件/AI/数据/网安",
          "recommendation": "高优先",
          "expertScore": 111,
          "sourceLevel": "B",
          "admissionCategory": "普通类",
          "isCoverageAudit": false,
          "notes": "当前库仅有2025最低分，平均分/最高分缺失，需补哈工大威海官方或省考试院分专业录取明细；含计算机、人工智能、网安、自动化、通信、电子、集成电路、电气等；可申请除拔尖班外全校范围转专业，需通过考核。",
          "planMatchType": "2025候选基线",
          "matched2025Major": "工科试验班（AI加先进技术领军班）",
          "riskTags": [
            "大类分流/专业清待核"
          ],
          "priorityGroups": [
            "C9",
            "国防七子"
          ],
          "focusOrder": 3,
          "action": "强校异地校区重点关注，先核普通批可报专业、校区安排、毕业证和转专业。"
        }
      ]
    },
    {
      "schoolKey": "hitsz",
      "school": "哈尔滨工业大学（深圳）",
      "priority": 4,
      "conclusion": "哈工大深圳当前近分线索主要来自卓越优才计划，本版先从普通类主方案屏蔽；若招生办确认2026陕西普通批可报，再作为高风险冲刺单独加回。",
      "items": []
    }
  ],
  "rows": [
    {
      "schoolKey": "hit",
      "school": "哈尔滨工业大学",
      "shortName": "哈工大本部",
      "city": "哈尔滨",
      "tier": "985/C9/211/双一流",
      "major": "工科试验班（未来技术拔尖班）",
      "minScore": 679,
      "maxScore": 682,
      "avgScore": 680.3,
      "rank": 0,
      "plan": 0,
      "planYear": 2026,
      "scoreGap": 17,
      "rankGap": -1558,
      "band": "极高冲刺",
      "track": "未来技术/强工科/哈工大本部",
      "recommendation": "极高冲刺",
      "expertScore": 82,
      "sourceLevel": "A",
      "admissionCategory": "普通类",
      "isCoverageAudit": false,
      "notes": "哈工大官方录取分数接口：2025陕西校本部物理+化学普通类，未来技术拔尖班最低679；校本部普通物理类最低679、平均681.5、最高687。640-660按普通批本部基本不匹配，只作高分冲刺和校方咨询参考。",
      "planMatchType": "2025候选基线",
      "matched2025Major": "工科试验班（未来技术拔尖班）",
      "riskTags": [
        "大类分流/专业清待核"
      ],
      "priorityGroups": [
        "C9",
        "国防七子"
      ],
      "focusOrder": 1,
      "action": "只留极高冲刺和招生办咨询，不能当稳项。"
    },
    {
      "schoolKey": "xjtu",
      "school": "西安交通大学",
      "shortName": "西交大",
      "city": "西安",
      "tier": "985/C9/双一流",
      "major": "具身智能",
      "minScore": 678,
      "avgScore": 680,
      "maxScore": 682,
      "rank": 536,
      "maxRank": 392,
      "plan": 9,
      "planYear": 2026,
      "scoreGap": 16,
      "rankGap": -1022,
      "band": "极高冲刺",
      "track": "计算机/软件/AI/数据/网安",
      "recommendation": "极高冲刺",
      "expertScore": 107,
      "sourceLevel": "A",
      "admissionCategory": "普通类",
      "isCoverageAudit": false,
      "notes": "2026计划专业；2025近似匹配：人工智能（新工科卓越计划），最低678、平均680、最高682。",
      "planMatchType": "近似匹配",
      "matched2025Major": "人工智能（新工科卓越计划）",
      "riskTags": [
        "2025近似专业"
      ],
      "priorityGroups": [
        "C9"
      ],
      "focusOrder": 2
    },
    {
      "schoolKey": "xjtu",
      "school": "西安交通大学",
      "shortName": "西交大",
      "city": "西安",
      "tier": "985/C9/双一流",
      "major": "人工智能（新工科卓越计划）",
      "minScore": 678,
      "avgScore": 680,
      "maxScore": 682,
      "rank": 536,
      "maxRank": 392,
      "plan": 4,
      "planYear": 2026,
      "scoreGap": 16,
      "rankGap": -1022,
      "band": "极高冲刺",
      "track": "计算机/软件/AI/数据/网安",
      "recommendation": "极高冲刺",
      "expertScore": 107,
      "sourceLevel": "A",
      "admissionCategory": "普通类",
      "isCoverageAudit": false,
      "notes": "2026计划专业；2025同名匹配：人工智能（新工科卓越计划），最低678、平均680、最高682。",
      "planMatchType": "同名匹配",
      "matched2025Major": "人工智能（新工科卓越计划）",
      "riskTags": [],
      "priorityGroups": [
        "C9"
      ],
      "focusOrder": 2
    },
    {
      "schoolKey": "xjtu",
      "school": "西安交通大学",
      "shortName": "西交大",
      "city": "西安",
      "tier": "985/C9/双一流",
      "major": "电子科学与技术",
      "minScore": 663,
      "avgScore": 665,
      "maxScore": 669,
      "rank": 1379,
      "maxRank": 993,
      "plan": 36,
      "planYear": 2026,
      "scoreGap": 1,
      "rankGap": -179,
      "band": "冲刺",
      "track": "电子信息/通信/集成电路/电气",
      "recommendation": "冲刺",
      "expertScore": 0,
      "sourceLevel": "A",
      "admissionCategory": "普通类",
      "isCoverageAudit": false,
      "notes": "2026计划专业；2025同名匹配：电子科学与技术，最低663、平均665、最高669。",
      "planMatchType": "同名匹配",
      "matched2025Major": "电子科学与技术",
      "riskTags": [],
      "priorityGroups": [
        "C9"
      ],
      "focusOrder": 2
    },
    {
      "schoolKey": "xjtu",
      "school": "西安交通大学",
      "shortName": "西交大",
      "city": "西安",
      "tier": "985/C9/双一流",
      "major": "微电子科学与工程",
      "minScore": 665,
      "avgScore": 666,
      "maxScore": 673,
      "rank": 1240,
      "maxRank": 771,
      "plan": 48,
      "planYear": 2026,
      "scoreGap": 3,
      "rankGap": -318,
      "band": "冲刺",
      "track": "电子信息/通信/集成电路/电气",
      "recommendation": "冲刺",
      "expertScore": 113,
      "sourceLevel": "A",
      "admissionCategory": "普通类",
      "isCoverageAudit": false,
      "notes": "2026计划专业；2025同名匹配：微电子科学与工程，最低665、平均666、最高673。",
      "planMatchType": "同名匹配",
      "matched2025Major": "微电子科学与工程",
      "riskTags": [],
      "priorityGroups": [
        "C9"
      ],
      "focusOrder": 2
    },
    {
      "schoolKey": "xjtu",
      "school": "西安交通大学",
      "shortName": "西交大",
      "city": "西安",
      "tier": "985/C9/双一流",
      "major": "工科试验班（计算机科学技术类）",
      "minScore": 666,
      "avgScore": 668,
      "maxScore": 673,
      "rank": 1165,
      "maxRank": 771,
      "plan": 27,
      "planYear": 2026,
      "scoreGap": 4,
      "rankGap": -393,
      "band": "冲刺",
      "track": "计算机/软件/AI/数据/网安",
      "recommendation": "冲刺",
      "expertScore": 111,
      "sourceLevel": "A",
      "admissionCategory": "普通类",
      "isCoverageAudit": false,
      "notes": "2026计划专业；2025同名匹配：工科试验班（计算机科学技术类），最低666、平均668、最高673。",
      "planMatchType": "同名匹配",
      "matched2025Major": "工科试验班（计算机科学技术类）",
      "riskTags": [],
      "priorityGroups": [
        "C9"
      ],
      "focusOrder": 2
    },
    {
      "schoolKey": "xjtu",
      "school": "西安交通大学",
      "shortName": "西交大",
      "city": "西安",
      "tier": "985/C9/双一流",
      "major": "工科试验班（材料创新设计与智能制备国卓班）",
      "minScore": 666,
      "avgScore": 668,
      "maxScore": 674,
      "rank": 1165,
      "maxRank": 708,
      "plan": 4,
      "planYear": 2026,
      "scoreGap": 4,
      "rankGap": -393,
      "band": "冲刺",
      "track": "工科方向待核",
      "recommendation": "冲刺",
      "expertScore": 0,
      "sourceLevel": "A",
      "admissionCategory": "普通类",
      "isCoverageAudit": false,
      "notes": "2026计划专业；2025同名匹配：工科试验班（材料创新设计与智能制备国卓班），最低666、平均668、最高674。",
      "planMatchType": "同名匹配",
      "matched2025Major": "工科试验班（材料创新设计与智能制备国卓班）",
      "riskTags": [],
      "priorityGroups": [
        "C9"
      ],
      "focusOrder": 2
    },
    {
      "schoolKey": "xjtu",
      "school": "西安交通大学",
      "shortName": "西交大",
      "city": "西安",
      "tier": "985/C9/双一流",
      "major": "自动化",
      "minScore": 667,
      "avgScore": 669,
      "maxScore": 678,
      "rank": 1103,
      "maxRank": 536,
      "plan": 44,
      "planYear": 2026,
      "scoreGap": 5,
      "rankGap": -455,
      "band": "冲刺",
      "track": "自动化/机器人/智能制造/测控",
      "recommendation": "冲刺",
      "expertScore": 111,
      "sourceLevel": "A",
      "admissionCategory": "普通类",
      "isCoverageAudit": false,
      "notes": "2026计划专业；2025同名匹配：自动化，最低667、平均669、最高678。",
      "planMatchType": "同名匹配",
      "matched2025Major": "自动化",
      "riskTags": [],
      "priorityGroups": [
        "C9"
      ],
      "focusOrder": 2
    },
    {
      "schoolKey": "xjtu",
      "school": "西安交通大学",
      "shortName": "西交大",
      "city": "西安",
      "tier": "985/C9/双一流",
      "major": "电气工程及其自动化（智能电气领军班）",
      "minScore": 670,
      "avgScore": 673,
      "maxScore": 676,
      "rank": 932,
      "maxRank": 619,
      "plan": 81,
      "planYear": 2026,
      "scoreGap": 8,
      "rankGap": -626,
      "band": "冲刺",
      "track": "电子信息/通信/集成电路/电气",
      "recommendation": "冲刺",
      "expertScore": 0,
      "sourceLevel": "A",
      "admissionCategory": "普通类",
      "isCoverageAudit": false,
      "notes": "2026计划专业；2025近似匹配：工科试验班（电气类），最低670、平均673、最高676。",
      "planMatchType": "近似匹配",
      "matched2025Major": "工科试验班（电气类）",
      "riskTags": [
        "2025近似专业"
      ],
      "priorityGroups": [
        "C9"
      ],
      "focusOrder": 2
    },
    {
      "schoolKey": "xjtu",
      "school": "西安交通大学",
      "shortName": "西交大",
      "city": "西安",
      "tier": "985/C9/双一流",
      "major": "工科试验班（智能感知与仪器国卓班）",
      "minScore": 671,
      "avgScore": 674,
      "maxScore": 680,
      "rank": 882,
      "maxRank": 460,
      "plan": 5,
      "planYear": 2026,
      "scoreGap": 9,
      "rankGap": -676,
      "band": "冲刺",
      "track": "自动化/机器人/智能制造/测控",
      "recommendation": "冲刺",
      "expertScore": 0,
      "sourceLevel": "A",
      "admissionCategory": "普通类",
      "isCoverageAudit": false,
      "notes": "2026计划专业；2025同名匹配：工科试验班（智能感知与仪器国卓班），最低671、平均674、最高680。",
      "planMatchType": "同名匹配",
      "matched2025Major": "工科试验班（智能感知与仪器国卓班）",
      "riskTags": [],
      "priorityGroups": [
        "C9"
      ],
      "focusOrder": 2
    },
    {
      "schoolKey": "xjtu",
      "school": "西安交通大学",
      "shortName": "西交大",
      "city": "西安",
      "tier": "985/C9/双一流",
      "major": "信息工程",
      "minScore": 662,
      "avgScore": 663,
      "maxScore": 667,
      "rank": 1456,
      "maxRank": 1103,
      "plan": 44,
      "planYear": 2026,
      "scoreGap": 0,
      "rankGap": -102,
      "band": "贴线核心",
      "track": "电子信息/通信/集成电路/电气",
      "recommendation": "高优先",
      "expertScore": 117,
      "sourceLevel": "A",
      "admissionCategory": "普通类",
      "isCoverageAudit": false,
      "notes": "2026计划专业；2025同名匹配：信息工程，最低662、平均663、最高667。",
      "planMatchType": "同名匹配",
      "matched2025Major": "信息工程",
      "riskTags": [],
      "priorityGroups": [
        "C9"
      ],
      "focusOrder": 2
    },
    {
      "schoolKey": "xjtu",
      "school": "西安交通大学",
      "shortName": "西交大",
      "city": "西安",
      "tier": "985/C9/双一流",
      "major": "软件工程",
      "minScore": 660,
      "avgScore": 662,
      "maxScore": 666,
      "rank": 1626,
      "maxRank": 1165,
      "plan": 27,
      "planYear": 2026,
      "scoreGap": -2,
      "rankGap": 68,
      "band": "贴线核心",
      "track": "计算机/软件/AI/数据/网安",
      "recommendation": "高优先",
      "expertScore": 118,
      "sourceLevel": "A",
      "admissionCategory": "普通类",
      "isCoverageAudit": false,
      "notes": "2026计划专业；2025同名匹配：软件工程，最低660、平均662、最高666。",
      "planMatchType": "同名匹配",
      "matched2025Major": "软件工程",
      "riskTags": [],
      "priorityGroups": [
        "C9"
      ],
      "focusOrder": 2
    },
    {
      "schoolKey": "xjtu",
      "school": "西安交通大学",
      "shortName": "西交大",
      "city": "西安",
      "tier": "985/C9/双一流",
      "major": "工科试验班（智能感知与仪器）",
      "minScore": 660,
      "avgScore": 661,
      "maxScore": 663,
      "rank": 1626,
      "maxRank": 1379,
      "plan": 6,
      "planYear": 2026,
      "scoreGap": -2,
      "rankGap": 68,
      "band": "贴线核心",
      "track": "自动化/机器人/智能制造/测控",
      "recommendation": "高优先",
      "expertScore": 110,
      "sourceLevel": "A",
      "admissionCategory": "普通类",
      "isCoverageAudit": false,
      "notes": "2026计划专业；2025同名匹配：工科试验班（智能感知与仪器），最低660、平均661、最高663。",
      "planMatchType": "同名匹配",
      "matched2025Major": "工科试验班（智能感知与仪器）",
      "riskTags": [],
      "priorityGroups": [
        "C9"
      ],
      "focusOrder": 2
    },
    {
      "schoolKey": "xjtu",
      "school": "西安交通大学",
      "shortName": "西交大",
      "city": "西安",
      "tier": "985/C9/双一流",
      "major": "工科试验班（材料创新设计与智能制备）",
      "minScore": 658,
      "avgScore": 660,
      "maxScore": 663,
      "rank": 1794,
      "maxRank": 1379,
      "plan": 6,
      "planYear": 2026,
      "scoreGap": -4,
      "rankGap": 236,
      "band": "冲稳",
      "track": "工科方向待核",
      "recommendation": "高优先",
      "expertScore": 0,
      "sourceLevel": "A",
      "admissionCategory": "普通类",
      "isCoverageAudit": false,
      "notes": "2026计划专业；2025同名匹配：工科试验班（材料创新设计与智能制备），最低658、平均660、最高663。",
      "planMatchType": "同名匹配",
      "matched2025Major": "工科试验班（材料创新设计与智能制备）",
      "riskTags": [],
      "priorityGroups": [
        "C9"
      ],
      "focusOrder": 2
    },
    {
      "schoolKey": "xjtu",
      "school": "西安交通大学",
      "shortName": "西交大",
      "city": "西安",
      "tier": "985/C9/双一流",
      "major": "工科试验班（智能过程与装备国卓班）",
      "minScore": 655,
      "avgScore": 657,
      "maxScore": 660,
      "rank": 2051,
      "maxRank": 1626,
      "plan": 4,
      "planYear": 2026,
      "scoreGap": -7,
      "rankGap": 493,
      "band": "冲稳",
      "track": "工科方向待核",
      "recommendation": "高优先",
      "expertScore": 111,
      "sourceLevel": "A",
      "admissionCategory": "普通类",
      "isCoverageAudit": false,
      "notes": "2026计划专业；2025同名匹配：工科试验班（智能过程与装备国卓班），最低655、平均657、最高660。",
      "planMatchType": "同名匹配",
      "matched2025Major": "工科试验班（智能过程与装备国卓班）",
      "riskTags": [],
      "priorityGroups": [
        "C9"
      ],
      "focusOrder": 2
    },
    {
      "schoolKey": "xjtu",
      "school": "西安交通大学",
      "shortName": "西交大",
      "city": "西安",
      "tier": "985/C9/双一流",
      "major": "工科试验班（智慧能源领军班）",
      "minScore": 653,
      "avgScore": 658,
      "maxScore": 673,
      "rank": 2246,
      "maxRank": 771,
      "plan": 195,
      "planYear": 2026,
      "scoreGap": -9,
      "rankGap": 688,
      "band": "冲稳",
      "track": "能源/电气",
      "recommendation": "高优先",
      "expertScore": 0,
      "sourceLevel": "A",
      "admissionCategory": "普通类",
      "isCoverageAudit": false,
      "notes": "2026计划专业；2025近似匹配：工科试验班（智慧能源类），最低653、平均658、最高673。",
      "planMatchType": "近似匹配",
      "matched2025Major": "工科试验班（智慧能源类）",
      "riskTags": [
        "2025近似专业"
      ],
      "priorityGroups": [
        "C9"
      ],
      "focusOrder": 2
    },
    {
      "schoolKey": "xjtu",
      "school": "西安交通大学",
      "shortName": "西交大",
      "city": "西安",
      "tier": "985/C9/双一流",
      "major": "工科试验班（智慧能源国卓班）",
      "minScore": 653,
      "avgScore": 658,
      "maxScore": 673,
      "rank": 2246,
      "maxRank": 771,
      "plan": 7,
      "planYear": 2026,
      "scoreGap": -9,
      "rankGap": 688,
      "band": "冲稳",
      "track": "能源/电气",
      "recommendation": "高优先",
      "expertScore": 0,
      "sourceLevel": "A",
      "admissionCategory": "普通类",
      "isCoverageAudit": false,
      "notes": "2026计划专业；2025近似匹配：工科试验班（智慧能源类），最低653、平均658、最高673。",
      "planMatchType": "近似匹配",
      "matched2025Major": "工科试验班（智慧能源类）",
      "riskTags": [
        "2025近似专业"
      ],
      "priorityGroups": [
        "C9"
      ],
      "focusOrder": 2
    },
    {
      "schoolKey": "xjtu",
      "school": "西安交通大学",
      "shortName": "西交大",
      "city": "西安",
      "tier": "985/C9/双一流",
      "major": "工科试验班（航天航空领军班）",
      "minScore": 649,
      "avgScore": 654,
      "maxScore": 661,
      "rank": 2630,
      "maxRank": 1544,
      "plan": 27,
      "planYear": 2026,
      "scoreGap": -13,
      "rankGap": 1072,
      "band": "稳妥",
      "track": "低空/航空航天/无人系统",
      "recommendation": "高优先",
      "expertScore": 0,
      "sourceLevel": "A",
      "admissionCategory": "普通类",
      "isCoverageAudit": false,
      "notes": "2026计划专业；2025近似匹配：工科试验班（航天航空类），最低649、平均654、最高661。",
      "planMatchType": "近似匹配",
      "matched2025Major": "工科试验班（航天航空类）",
      "riskTags": [
        "2025近似专业"
      ],
      "priorityGroups": [
        "C9"
      ],
      "focusOrder": 2
    },
    {
      "schoolKey": "xjtu",
      "school": "西安交通大学",
      "shortName": "西交大",
      "city": "西安",
      "tier": "985/C9/双一流",
      "major": "工科试验班（智能制造领军班）",
      "minScore": 649,
      "avgScore": 655,
      "maxScore": 668,
      "rank": 2630,
      "maxRank": 1043,
      "plan": 104,
      "planYear": 2026,
      "scoreGap": -13,
      "rankGap": 1072,
      "band": "稳妥",
      "track": "自动化/机器人/智能制造/测控",
      "recommendation": "高优先",
      "expertScore": 0,
      "sourceLevel": "A",
      "admissionCategory": "普通类",
      "isCoverageAudit": false,
      "notes": "2026计划专业；2025近似匹配：工科试验班（智能制造类），最低649、平均655、最高668。",
      "planMatchType": "近似匹配",
      "matched2025Major": "工科试验班（智能制造类）",
      "riskTags": [
        "2025近似专业"
      ],
      "priorityGroups": [
        "C9"
      ],
      "focusOrder": 2
    },
    {
      "schoolKey": "hitwh",
      "school": "哈尔滨工业大学（威海）",
      "shortName": "哈工大威海",
      "city": "威海/哈尔滨",
      "tier": "985/C9/211/双一流",
      "major": "工科试验班（机器人与智能装备拔尖班）",
      "minScore": 650,
      "maxScore": 0,
      "avgScore": 0,
      "rank": 2629,
      "plan": 0,
      "planYear": 2026,
      "scoreGap": -12,
      "rankGap": 1071,
      "band": "稳妥",
      "track": "自动化/机器人/智能制造/测控",
      "recommendation": "高优先",
      "expertScore": 106,
      "sourceLevel": "B",
      "admissionCategory": "普通类",
      "isCoverageAudit": false,
      "notes": "当前库仅有2025最低分，平均分/最高分缺失，需补哈工大威海官方或省考试院分专业录取明细；本专业类内任选专业；EOL备注为前2年威海校区、后2年校本部，需以2026章程和招生办答复复核。",
      "planMatchType": "2025候选基线",
      "matched2025Major": "工科试验班（机器人与智能装备拔尖班）",
      "riskTags": [
        "大类分流/专业清待核"
      ],
      "priorityGroups": [
        "C9",
        "国防七子"
      ],
      "focusOrder": 3,
      "action": "强校异地校区重点关注，先核普通批可报专业、校区安排、毕业证和转专业。"
    },
    {
      "schoolKey": "hitwh",
      "school": "哈尔滨工业大学（威海）",
      "shortName": "哈工大威海",
      "city": "威海/哈尔滨",
      "tier": "985/C9/211/双一流",
      "major": "工科试验班（AI加先进技术领军班）",
      "minScore": 644,
      "maxScore": 0,
      "avgScore": 0,
      "rank": 3291,
      "plan": 0,
      "planYear": 2026,
      "scoreGap": -18,
      "rankGap": 1733,
      "band": "稳妥",
      "track": "计算机/软件/AI/数据/网安",
      "recommendation": "高优先",
      "expertScore": 111,
      "sourceLevel": "B",
      "admissionCategory": "普通类",
      "isCoverageAudit": false,
      "notes": "当前库仅有2025最低分，平均分/最高分缺失，需补哈工大威海官方或省考试院分专业录取明细；含计算机、人工智能、网安、自动化、通信、电子、集成电路、电气等；可申请除拔尖班外全校范围转专业，需通过考核。",
      "planMatchType": "2025候选基线",
      "matched2025Major": "工科试验班（AI加先进技术领军班）",
      "riskTags": [
        "大类分流/专业清待核"
      ],
      "priorityGroups": [
        "C9",
        "国防七子"
      ],
      "focusOrder": 3,
      "action": "强校异地校区重点关注，先核普通批可报专业、校区安排、毕业证和转专业。"
    },
    {
      "schoolKey": "uestc",
      "school": "电子科技大学",
      "shortName": "成电",
      "city": "成都",
      "tier": "985/双一流",
      "major": "电子信息类（“成电英才”电子与计算机科技创新领军人才计划）",
      "minScore": 675,
      "avgScore": 676.5,
      "maxScore": 678,
      "rank": 0,
      "maxRank": 0,
      "plan": 2,
      "planYear": 2026,
      "scoreGap": 13,
      "rankGap": null,
      "band": "极高冲刺",
      "track": "计算机/软件/AI/数据/网安",
      "recommendation": "极高冲刺",
      "expertScore": 0,
      "sourceLevel": "A",
      "admissionCategory": "普通类",
      "isCoverageAudit": false,
      "notes": "2026计划专业；2025同名匹配：电子信息类（“成电英才”电子与计算机科技创新领军人才计划），最低675、平均676.5、最高678。",
      "planMatchType": "同名匹配",
      "matched2025Major": "电子信息类（“成电英才”电子与计算机科技创新领军人才计划）",
      "riskTags": [],
      "priorityGroups": [
        "985重点"
      ],
      "focusOrder": 99
    },
    {
      "schoolKey": "uestc",
      "school": "电子科技大学",
      "shortName": "成电",
      "city": "成都",
      "tier": "985/双一流",
      "major": "计算机科学与技术（智能金融与区块链金融“双A”联合学位实验班）",
      "minScore": 668,
      "avgScore": 668,
      "maxScore": 668,
      "rank": 0,
      "maxRank": 0,
      "plan": 2,
      "planYear": 2026,
      "scoreGap": 6,
      "rankGap": null,
      "band": "冲刺",
      "track": "计算机/软件/AI/数据/网安",
      "recommendation": "冲刺",
      "expertScore": 0,
      "sourceLevel": "A",
      "admissionCategory": "普通类",
      "isCoverageAudit": false,
      "notes": "2026计划专业；2025同名匹配：计算机科学与技术（智能金融与区块链金融“双A”联合学位实验班），最低668、平均668、最高668。",
      "planMatchType": "同名匹配",
      "matched2025Major": "计算机科学与技术（智能金融与区块链金融“双A”联合学位实验班）",
      "riskTags": [],
      "priorityGroups": [
        "985重点"
      ],
      "focusOrder": 99
    },
    {
      "schoolKey": "seu",
      "school": "东南大学",
      "shortName": "东大",
      "city": "南京",
      "tier": "985/双一流",
      "major": "计算机类",
      "minScore": 662,
      "maxScore": 0,
      "avgScore": 0,
      "rank": 1543,
      "plan": 0,
      "planYear": 2026,
      "scoreGap": 0,
      "rankGap": -15,
      "band": "贴线核心",
      "track": "计算机/软件/AI/数据/网安",
      "recommendation": "高优先",
      "expertScore": 88,
      "sourceLevel": "B",
      "admissionCategory": "普通类",
      "isCoverageAudit": false,
      "notes": "2025陕西物理普通批候选基线；当前仓库未接入东南大学官方分专业接口，需回东南招生网或陕西省考试院复核专业线。660段以上可讨论，650段不作为主稳。",
      "planMatchType": "2025候选基线",
      "matched2025Major": "计算机类",
      "riskTags": [
        "大类分流/专业清待核"
      ],
      "priorityGroups": [
        "中坚九校"
      ],
      "focusOrder": 99,
      "action": "分数贴近，可作冲刺比较项。"
    },
    {
      "schoolKey": "seu",
      "school": "东南大学",
      "shortName": "东大",
      "city": "南京",
      "tier": "985/双一流",
      "major": "工科试验班（智能制造与智能系统）",
      "minScore": 662,
      "maxScore": 0,
      "avgScore": 0,
      "rank": 1543,
      "plan": 0,
      "planYear": 2026,
      "scoreGap": 0,
      "rankGap": -15,
      "band": "贴线核心",
      "track": "自动化/机器人/智能制造/测控",
      "recommendation": "高优先",
      "expertScore": 85,
      "sourceLevel": "B",
      "admissionCategory": "普通类",
      "isCoverageAudit": false,
      "notes": "2025陕西物理普通批候选基线；当前仓库未接入东南大学官方分专业接口，需回东南招生网或陕西省考试院复核专业线。普通批偏高，当前只按普通批口径判断。",
      "planMatchType": "2025候选基线",
      "matched2025Major": "工科试验班（智能制造与智能系统）",
      "riskTags": [
        "大类分流/专业清待核"
      ],
      "priorityGroups": [
        "中坚九校"
      ],
      "focusOrder": 99,
      "action": "分数贴近，可作冲刺比较项。"
    },
    {
      "schoolKey": "whu",
      "school": "武汉大学",
      "shortName": "武大",
      "city": "武汉",
      "tier": "985/双一流",
      "major": "计算机类（国家网络安全学院）",
      "minScore": 661,
      "maxScore": 0,
      "avgScore": 0,
      "rank": 1625,
      "plan": 0,
      "planYear": 2026,
      "scoreGap": -1,
      "rankGap": 67,
      "band": "贴线核心",
      "track": "计算机/软件/AI/数据/网安",
      "recommendation": "高优先",
      "expertScore": 85,
      "sourceLevel": "B",
      "admissionCategory": "普通类",
      "isCoverageAudit": false,
      "notes": "2025陕西物理普通批；660段可冲，650段风险较高。",
      "planMatchType": "2025候选基线",
      "matched2025Major": "计算机类（国家网络安全学院）",
      "riskTags": [
        "大类分流/专业清待核"
      ],
      "priorityGroups": [
        "985重点"
      ],
      "focusOrder": 99,
      "action": "分数贴近，可作冲刺比较项。"
    },
    {
      "schoolKey": "hust",
      "school": "华中科技大学",
      "shortName": "华科",
      "city": "武汉",
      "tier": "985/双一流",
      "major": "光电信息科学与工程",
      "minScore": 660,
      "maxScore": 0,
      "avgScore": 0,
      "rank": 1704,
      "plan": 0,
      "planYear": 2026,
      "scoreGap": -2,
      "rankGap": 146,
      "band": "贴线核心",
      "track": "电子信息/通信/集成电路",
      "recommendation": "高优先",
      "expertScore": 90,
      "sourceLevel": "B",
      "admissionCategory": "普通类",
      "isCoverageAudit": false,
      "notes": "2025陕西物理普通批；华科强工科冲刺项。",
      "planMatchType": "2025候选基线",
      "matched2025Major": "光电信息科学与工程",
      "riskTags": [],
      "priorityGroups": [
        "中坚九校"
      ],
      "focusOrder": 99,
      "action": "分数贴近，可作冲刺比较项。"
    },
    {
      "schoolKey": "whu",
      "school": "武汉大学",
      "shortName": "武大",
      "city": "武汉",
      "tier": "985/双一流",
      "major": "工科试验班（电气类）",
      "minScore": 660,
      "maxScore": 0,
      "avgScore": 0,
      "rank": 1704,
      "plan": 0,
      "planYear": 2026,
      "scoreGap": -2,
      "rankGap": 146,
      "band": "贴线核心",
      "track": "能源/电气",
      "recommendation": "优先",
      "expertScore": 76,
      "sourceLevel": "B",
      "admissionCategory": "普通类",
      "isCoverageAudit": false,
      "notes": "2025陕西物理普通批；电气和储能方向强，但650段不宜当稳项。",
      "planMatchType": "2025候选基线",
      "matched2025Major": "工科试验班（电气类）",
      "riskTags": [
        "大类分流/专业清待核"
      ],
      "priorityGroups": [
        "985重点"
      ],
      "focusOrder": 99,
      "action": "分数贴近，可作冲刺比较项。"
    },
    {
      "schoolKey": "uestc",
      "school": "电子科技大学",
      "shortName": "成电",
      "city": "成都",
      "tier": "985/双一流",
      "major": "电子信息类（信息与通信）",
      "minScore": 659,
      "avgScore": 660.6,
      "maxScore": 669,
      "rank": 0,
      "maxRank": 0,
      "plan": 11,
      "planYear": 2026,
      "scoreGap": -3,
      "rankGap": null,
      "band": "冲稳",
      "track": "电子信息/通信/集成电路/电气",
      "recommendation": "高优先",
      "expertScore": 87,
      "sourceLevel": "A",
      "admissionCategory": "普通类",
      "isCoverageAudit": false,
      "notes": "2026计划专业；2025同名匹配：电子信息类（信息与通信），最低659、平均660.6、最高669。",
      "planMatchType": "同名匹配",
      "matched2025Major": "电子信息类（信息与通信）",
      "riskTags": [],
      "priorityGroups": [
        "985重点"
      ],
      "focusOrder": 99
    },
    {
      "schoolKey": "whu",
      "school": "武汉大学",
      "shortName": "武大",
      "city": "武汉",
      "tier": "985/双一流",
      "major": "微电子科学与工程（集成电路学院）",
      "minScore": 658,
      "maxScore": 0,
      "avgScore": 0,
      "rank": 1873,
      "plan": 0,
      "planYear": 2026,
      "scoreGap": -4,
      "rankGap": 315,
      "band": "冲稳",
      "track": "电子信息/通信/集成电路",
      "recommendation": "高优先",
      "expertScore": 90,
      "sourceLevel": "B",
      "admissionCategory": "普通类",
      "isCoverageAudit": false,
      "notes": "2025陕西物理普通批；读研收益明显。",
      "planMatchType": "2025候选基线",
      "matched2025Major": "微电子科学与工程（集成电路学院）",
      "riskTags": [],
      "priorityGroups": [
        "985重点"
      ],
      "focusOrder": 99,
      "action": "分数接近，可作冲稳比较项。"
    },
    {
      "schoolKey": "uestc",
      "school": "电子科技大学",
      "shortName": "成电",
      "city": "成都",
      "tier": "985/双一流",
      "major": "工科试验班（电子工程类）",
      "minScore": 658,
      "avgScore": 660.6,
      "maxScore": 666,
      "rank": 0,
      "maxRank": 0,
      "plan": 8,
      "planYear": 2026,
      "scoreGap": -4,
      "rankGap": null,
      "band": "冲稳",
      "track": "电子信息/通信/集成电路/电气",
      "recommendation": "高优先",
      "expertScore": 87,
      "sourceLevel": "A",
      "admissionCategory": "普通类",
      "isCoverageAudit": false,
      "notes": "2026计划专业；2025同名匹配：工科试验班（电子工程类），最低658、平均660.6、最高666。",
      "planMatchType": "同名匹配",
      "matched2025Major": "工科试验班（电子工程类）",
      "riskTags": [],
      "priorityGroups": [
        "985重点"
      ],
      "focusOrder": 99
    },
    {
      "schoolKey": "whu",
      "school": "武汉大学",
      "shortName": "武大",
      "city": "武汉",
      "tier": "985/双一流",
      "major": "电子信息类（电子信息学院）",
      "minScore": 658,
      "maxScore": 0,
      "avgScore": 0,
      "rank": 1873,
      "plan": 0,
      "planYear": 2026,
      "scoreGap": -4,
      "rankGap": 315,
      "band": "冲稳",
      "track": "电子信息/通信/集成电路",
      "recommendation": "高优先",
      "expertScore": 87,
      "sourceLevel": "B",
      "admissionCategory": "普通类",
      "isCoverageAudit": false,
      "notes": "2025陕西物理普通批；含电子信息、通信及人工智能试验班相关方向。",
      "planMatchType": "2025候选基线",
      "matched2025Major": "电子信息类（电子信息学院）",
      "riskTags": [
        "大类分流/专业清待核"
      ],
      "priorityGroups": [
        "985重点"
      ],
      "focusOrder": 99,
      "action": "分数接近，可作冲稳比较项。"
    },
    {
      "schoolKey": "hust",
      "school": "华中科技大学",
      "shortName": "华科",
      "city": "武汉",
      "tier": "985/双一流",
      "major": "机械类",
      "minScore": 658,
      "maxScore": 0,
      "avgScore": 0,
      "rank": 1873,
      "plan": 0,
      "planYear": 2026,
      "scoreGap": -4,
      "rankGap": 315,
      "band": "冲稳",
      "track": "自动化/机器人/智能制造/测控",
      "recommendation": "高优先",
      "expertScore": 86,
      "sourceLevel": "B",
      "admissionCategory": "普通类",
      "isCoverageAudit": false,
      "notes": "2025陕西物理普通批；强工科平台，但与计算机/电子相比职业弹性略低。",
      "planMatchType": "2025候选基线",
      "matched2025Major": "机械类",
      "riskTags": [
        "大类分流/专业清待核",
        "近视度数不宜就读待核"
      ],
      "priorityGroups": [
        "中坚九校"
      ],
      "focusOrder": 99,
      "action": "分数接近，可作冲稳比较项。"
    },
    {
      "schoolKey": "hust",
      "school": "华中科技大学",
      "shortName": "华科",
      "city": "武汉",
      "tier": "985/双一流",
      "major": "航空航天类",
      "minScore": 655,
      "maxScore": 0,
      "avgScore": 0,
      "rank": 2144,
      "plan": 0,
      "planYear": 2026,
      "scoreGap": -7,
      "rankGap": 586,
      "band": "冲稳",
      "track": "低空/航空航天/无人系统",
      "recommendation": "高优先",
      "expertScore": 82,
      "sourceLevel": "B",
      "admissionCategory": "普通类",
      "isCoverageAudit": false,
      "notes": "2025陕西物理普通批；课程硬，适合作为高分冲刺而非稳保。",
      "planMatchType": "2025候选基线",
      "matched2025Major": "航空航天类",
      "riskTags": [
        "大类分流/专业清待核"
      ],
      "priorityGroups": [
        "中坚九校"
      ],
      "focusOrder": 99,
      "action": "分数接近，可作冲稳比较项。"
    },
    {
      "schoolKey": "uestc",
      "school": "电子科技大学",
      "shortName": "成电",
      "city": "成都",
      "tier": "985/双一流",
      "major": "集成电路设计与集成系统（国家示范性微电子学院）",
      "minScore": 655,
      "avgScore": 656.6,
      "maxScore": 663,
      "rank": 0,
      "maxRank": 0,
      "plan": 13,
      "planYear": 2026,
      "scoreGap": -7,
      "rankGap": null,
      "band": "冲稳",
      "track": "电子信息/通信/集成电路/电气",
      "recommendation": "高优先",
      "expertScore": 0,
      "sourceLevel": "A",
      "admissionCategory": "普通类",
      "isCoverageAudit": false,
      "notes": "2026计划专业；2025同名匹配：集成电路设计与集成系统（国家示范性微电子学院），最低655、平均656.6、最高663。",
      "planMatchType": "同名匹配",
      "matched2025Major": "集成电路设计与集成系统（国家示范性微电子学院）",
      "riskTags": [],
      "priorityGroups": [
        "985重点"
      ],
      "focusOrder": 99
    },
    {
      "schoolKey": "uestc",
      "school": "电子科技大学",
      "shortName": "成电",
      "city": "成都",
      "tier": "985/双一流",
      "major": "微电子科学与工程",
      "minScore": 655,
      "avgScore": 656.6,
      "maxScore": 663,
      "rank": 0,
      "maxRank": 0,
      "plan": 3,
      "planYear": 2026,
      "scoreGap": -7,
      "rankGap": null,
      "band": "冲稳",
      "track": "电子信息/通信/集成电路/电气",
      "recommendation": "高优先",
      "expertScore": 0,
      "sourceLevel": "A",
      "admissionCategory": "普通类",
      "isCoverageAudit": false,
      "notes": "2026计划专业；2025近似匹配：集成电路设计与集成系统（国家示范性微电子学院），最低655、平均656.6、最高663。",
      "planMatchType": "近似匹配",
      "matched2025Major": "集成电路设计与集成系统（国家示范性微电子学院）",
      "riskTags": [
        "2025近似专业"
      ],
      "priorityGroups": [
        "985重点"
      ],
      "focusOrder": 99
    },
    {
      "schoolKey": "uestc",
      "school": "电子科技大学",
      "shortName": "成电",
      "city": "成都",
      "tier": "985/双一流",
      "major": "计算机类",
      "minScore": 653,
      "avgScore": 656.2,
      "maxScore": 661,
      "rank": 0,
      "maxRank": 0,
      "plan": 6,
      "planYear": 2026,
      "scoreGap": -9,
      "rankGap": null,
      "band": "冲稳",
      "track": "计算机/软件/AI/数据/网安",
      "recommendation": "高优先",
      "expertScore": 91,
      "sourceLevel": "A",
      "admissionCategory": "普通类",
      "isCoverageAudit": false,
      "notes": "2026计划专业；2025同名匹配：计算机类，最低653、平均656.2、最高661。",
      "planMatchType": "同名匹配",
      "matched2025Major": "计算机类",
      "riskTags": [],
      "priorityGroups": [
        "985重点"
      ],
      "focusOrder": 99
    },
    {
      "schoolKey": "nwpu",
      "school": "西北工业大学",
      "shortName": "西工大",
      "city": "西安",
      "tier": "985/双一流",
      "major": "计算机类（计算机，含智能交互设计）",
      "minScore": 652,
      "maxScore": 0,
      "avgScore": 0,
      "rank": 2447,
      "plan": 0,
      "planYear": 2026,
      "scoreGap": -10,
      "rankGap": 889,
      "band": "冲稳",
      "track": "计算机/软件/AI/数据/网安",
      "recommendation": "高优先",
      "expertScore": 96,
      "sourceLevel": "B",
      "admissionCategory": "普通类",
      "isCoverageAudit": false,
      "notes": "愿意训练编程，未来AI时代需要系统能力和工程基本功。",
      "planMatchType": "2025候选基线",
      "matched2025Major": "计算机类（计算机，含智能交互设计）",
      "riskTags": [
        "大类分流/专业清待核"
      ],
      "priorityGroups": [
        "国防七子",
        "中坚九校"
      ],
      "focusOrder": 99,
      "action": "分数接近，可作冲稳比较项。"
    },
    {
      "schoolKey": "tju",
      "school": "天津大学",
      "shortName": "天大",
      "city": "天津",
      "tier": "985/双一流",
      "major": "工科试验班（未来技术学院）",
      "minScore": 652,
      "maxScore": 0,
      "avgScore": 0,
      "rank": 2447,
      "plan": 0,
      "planYear": 2026,
      "scoreGap": -10,
      "rankGap": 889,
      "band": "冲稳",
      "track": "自动化/机器人/智能制造/测控",
      "recommendation": "高优先",
      "expertScore": 84,
      "sourceLevel": "B",
      "admissionCategory": "普通类",
      "isCoverageAudit": false,
      "notes": "2025陕西物理普通批；面向人工智能、新型储能、智能制造、具身智能等，属于高价值遗漏项。",
      "planMatchType": "2025候选基线",
      "matched2025Major": "工科试验班（未来技术学院）",
      "riskTags": [
        "大类分流/专业清待核"
      ],
      "priorityGroups": [
        "中坚九校"
      ],
      "focusOrder": 99,
      "action": "分数接近，可作冲稳比较项。"
    },
    {
      "schoolKey": "uestc",
      "school": "电子科技大学",
      "shortName": "成电",
      "city": "成都",
      "tier": "985/双一流",
      "major": "工科试验班（机器人、电气信息、智能制造）",
      "minScore": 651,
      "avgScore": 652,
      "maxScore": 653,
      "rank": 0,
      "maxRank": 0,
      "plan": 3,
      "planYear": 2026,
      "scoreGap": -11,
      "rankGap": null,
      "band": "稳妥",
      "track": "电子信息/通信/集成电路/电气",
      "recommendation": "高优先",
      "expertScore": 90,
      "sourceLevel": "A",
      "admissionCategory": "普通类",
      "isCoverageAudit": false,
      "notes": "2026计划专业；2025同名匹配：工科试验班（机器人、电气信息、智能制造），最低651、平均652、最高653。",
      "planMatchType": "同名匹配",
      "matched2025Major": "工科试验班（机器人、电气信息、智能制造）",
      "riskTags": [],
      "priorityGroups": [
        "985重点"
      ],
      "focusOrder": 99
    },
    {
      "schoolKey": "nwpu",
      "school": "西北工业大学",
      "shortName": "西工大",
      "city": "西安",
      "tier": "985/双一流",
      "major": "航空航天类（航空）",
      "minScore": 651,
      "maxScore": 0,
      "avgScore": 0,
      "rank": 2550,
      "plan": 0,
      "planYear": 2026,
      "scoreGap": -11,
      "rankGap": 992,
      "band": "稳妥",
      "track": "低空/航空航天/无人系统",
      "recommendation": "高优先",
      "expertScore": 87,
      "sourceLevel": "B",
      "admissionCategory": "普通类",
      "isCoverageAudit": false,
      "notes": "方向有前景但课程硬、行业周期和名额波动要谨慎。",
      "planMatchType": "2025候选基线",
      "matched2025Major": "航空航天类（航空）",
      "riskTags": [
        "大类分流/专业清待核"
      ],
      "priorityGroups": [
        "国防七子",
        "中坚九校"
      ],
      "focusOrder": 99,
      "action": "作为985好专业横向比较项，防止只盯重点校漏掉强专业。"
    },
    {
      "schoolKey": "uestc",
      "school": "电子科技大学",
      "shortName": "成电",
      "city": "成都",
      "tier": "985/双一流",
      "major": "电子信息类（光电集成与光网络）",
      "minScore": 650,
      "avgScore": 651.5,
      "maxScore": 653,
      "rank": 0,
      "maxRank": 0,
      "plan": 2,
      "planYear": 2026,
      "scoreGap": -12,
      "rankGap": null,
      "band": "稳妥",
      "track": "电子信息/通信/集成电路/电气",
      "recommendation": "高优先",
      "expertScore": 0,
      "sourceLevel": "A",
      "admissionCategory": "普通类",
      "isCoverageAudit": false,
      "notes": "2026计划专业；2025同名匹配：电子信息类（光电集成与光网络），最低650、平均651.5、最高653。",
      "planMatchType": "同名匹配",
      "matched2025Major": "电子信息类（光电集成与光网络）",
      "riskTags": [],
      "priorityGroups": [
        "985重点"
      ],
      "focusOrder": 99
    },
    {
      "schoolKey": "uestc",
      "school": "电子科技大学",
      "shortName": "成电",
      "city": "成都",
      "tier": "985/双一流",
      "major": "电子信息类（智能仪器、智能控制）",
      "minScore": 649,
      "avgScore": 650,
      "maxScore": 652,
      "rank": 0,
      "maxRank": 0,
      "plan": 4,
      "planYear": 2026,
      "scoreGap": -13,
      "rankGap": null,
      "band": "稳妥",
      "track": "电子信息/通信/集成电路/电气",
      "recommendation": "高优先",
      "expertScore": 88,
      "sourceLevel": "A",
      "admissionCategory": "普通类",
      "isCoverageAudit": false,
      "notes": "2026计划专业；2025同名匹配：电子信息类（智能仪器、智能控制），最低649、平均650、最高652。",
      "planMatchType": "同名匹配",
      "matched2025Major": "电子信息类（智能仪器、智能控制）",
      "riskTags": [],
      "priorityGroups": [
        "985重点"
      ],
      "focusOrder": 99
    },
    {
      "schoolKey": "nwpu",
      "school": "西北工业大学",
      "shortName": "西工大",
      "city": "西安",
      "tier": "985/双一流",
      "major": "计算机类（网络安全）",
      "minScore": 648,
      "maxScore": 0,
      "avgScore": 0,
      "rank": 2829,
      "plan": 0,
      "planYear": 2026,
      "scoreGap": -14,
      "rankGap": 1271,
      "band": "稳妥",
      "track": "计算机/软件/AI/数据/网安",
      "recommendation": "高优先",
      "expertScore": 96,
      "sourceLevel": "B",
      "admissionCategory": "普通类",
      "isCoverageAudit": false,
      "notes": "愿意训练编程，未来AI时代需要系统能力和工程基本功。",
      "planMatchType": "2025候选基线",
      "matched2025Major": "计算机类（网络安全）",
      "riskTags": [
        "大类分流/专业清待核"
      ],
      "priorityGroups": [
        "国防七子",
        "中坚九校"
      ],
      "focusOrder": 99,
      "action": "作为985好专业横向比较项，防止只盯重点校漏掉强专业。"
    },
    {
      "schoolKey": "dlut",
      "school": "大连理工大学",
      "shortName": "大工",
      "city": "大连",
      "tier": "985/双一流",
      "major": "人工智能（新工科大师班）",
      "minScore": 648,
      "maxScore": 0,
      "avgScore": 0,
      "rank": 0,
      "plan": 0,
      "planYear": 2026,
      "scoreGap": -14,
      "rankGap": -1558,
      "band": "稳妥",
      "track": "计算机/软件/AI/数据/网安",
      "recommendation": "高优先",
      "expertScore": 93,
      "sourceLevel": "B",
      "admissionCategory": "普通类",
      "isCoverageAudit": false,
      "notes": "愿意训练编程，未来AI时代需要系统能力和工程基本功。",
      "planMatchType": "2025候选基线",
      "matched2025Major": "人工智能（新工科大师班）",
      "riskTags": [],
      "priorityGroups": [
        "985重点"
      ],
      "focusOrder": 99,
      "action": "作为985好专业横向比较项，防止只盯重点校漏掉强专业。"
    },
    {
      "schoolKey": "tju",
      "school": "天津大学",
      "shortName": "天大",
      "city": "天津",
      "tier": "985/双一流",
      "major": "工科试验班（智能与计算类）",
      "minScore": 648,
      "maxScore": 0,
      "avgScore": 0,
      "rank": 2829,
      "plan": 0,
      "planYear": 2026,
      "scoreGap": -14,
      "rankGap": 1271,
      "band": "稳妥",
      "track": "计算机/软件/AI/数据/网安",
      "recommendation": "高优先",
      "expertScore": 91,
      "sourceLevel": "B",
      "admissionCategory": "普通类",
      "isCoverageAudit": false,
      "notes": "2025陕西物理普通批；软件工程后两年收费需复核。",
      "planMatchType": "2025候选基线",
      "matched2025Major": "工科试验班（智能与计算类）",
      "riskTags": [
        "大类分流/专业清待核"
      ],
      "priorityGroups": [
        "中坚九校"
      ],
      "focusOrder": 99,
      "action": "作为985好专业横向比较项，防止只盯重点校漏掉强专业。"
    },
    {
      "schoolKey": "nwpu",
      "school": "西北工业大学",
      "shortName": "西工大",
      "city": "西安",
      "tier": "985/双一流",
      "major": "民用航空含低空技术与工程",
      "minScore": 648,
      "maxScore": 0,
      "avgScore": 0,
      "rank": 2829,
      "plan": 0,
      "planYear": 2026,
      "scoreGap": -14,
      "rankGap": 1271,
      "band": "稳妥",
      "track": "低空/航空航天/无人系统",
      "recommendation": "高优先",
      "expertScore": 90,
      "sourceLevel": "B",
      "admissionCategory": "普通类",
      "isCoverageAudit": false,
      "notes": "方向有前景但课程硬、行业周期和名额波动要谨慎。",
      "planMatchType": "2025候选基线",
      "matched2025Major": "民用航空含低空技术与工程",
      "riskTags": [],
      "priorityGroups": [
        "国防七子",
        "中坚九校"
      ],
      "focusOrder": 99,
      "action": "作为985好专业横向比较项，防止只盯重点校漏掉强专业。"
    },
    {
      "schoolKey": "nwpu",
      "school": "西北工业大学",
      "shortName": "西工大",
      "city": "西安",
      "tier": "985/双一流",
      "major": "电子信息类（电子信息）",
      "minScore": 647,
      "maxScore": 0,
      "avgScore": 0,
      "rank": 0,
      "plan": 0,
      "planYear": 2026,
      "scoreGap": -15,
      "rankGap": -1558,
      "band": "稳妥",
      "track": "电子信息/通信/集成电路",
      "recommendation": "高优先",
      "expertScore": 97,
      "sourceLevel": "B",
      "admissionCategory": "普通类",
      "isCoverageAudit": false,
      "notes": "接受电路信号控制，且西电、成电、北邮、西工大等平台强。",
      "planMatchType": "2025候选基线",
      "matched2025Major": "电子信息类（电子信息）",
      "riskTags": [
        "大类分流/专业清待核"
      ],
      "priorityGroups": [
        "国防七子",
        "中坚九校"
      ],
      "focusOrder": 99,
      "action": "作为985好专业横向比较项，防止只盯重点校漏掉强专业。"
    },
    {
      "schoolKey": "nwpu",
      "school": "西北工业大学",
      "shortName": "西工大",
      "city": "西安",
      "tier": "985/双一流",
      "major": "自动化类",
      "minScore": 646,
      "maxScore": 0,
      "avgScore": 0,
      "rank": 0,
      "plan": 0,
      "planYear": 2026,
      "scoreGap": -16,
      "rankGap": -1558,
      "band": "稳妥",
      "track": "自动化/机器人/智能制造/测控",
      "recommendation": "高优先",
      "expertScore": 95,
      "sourceLevel": "B",
      "admissionCategory": "普通类",
      "isCoverageAudit": false,
      "notes": "工程应用强，和制造业升级、机器人、工业AI相关。",
      "planMatchType": "2025候选基线",
      "matched2025Major": "自动化类",
      "riskTags": [
        "大类分流/专业清待核"
      ],
      "priorityGroups": [
        "国防七子",
        "中坚九校"
      ],
      "focusOrder": 99,
      "action": "作为985好专业横向比较项，防止只盯重点校漏掉强专业。"
    },
    {
      "schoolKey": "scut",
      "school": "华南理工大学",
      "shortName": "华工",
      "city": "广州",
      "tier": "985/双一流",
      "major": "工科试验班（卓越人才班）",
      "minScore": 645,
      "maxScore": 0,
      "avgScore": 0,
      "rank": 3161,
      "plan": 0,
      "planYear": 2026,
      "scoreGap": -17,
      "rankGap": 1603,
      "band": "稳妥",
      "track": "计算机/软件/AI/数据/网安",
      "recommendation": "高优先",
      "expertScore": 96,
      "sourceLevel": "B",
      "admissionCategory": "普通类",
      "isCoverageAudit": false,
      "notes": "2025陕西物理普通批；华南强工科平台，640-650段重点补充。",
      "planMatchType": "2025候选基线",
      "matched2025Major": "工科试验班（卓越人才班）",
      "riskTags": [
        "大类分流/专业清待核"
      ],
      "priorityGroups": [
        "中坚九校"
      ],
      "focusOrder": 99,
      "action": "作为985好专业横向比较项，防止只盯重点校漏掉强专业。"
    },
    {
      "schoolKey": "tju",
      "school": "天津大学",
      "shortName": "天大",
      "city": "天津",
      "tier": "985/双一流",
      "major": "工科试验班（电气信息类）",
      "minScore": 642,
      "maxScore": 0,
      "avgScore": 0,
      "rank": 3537,
      "plan": 0,
      "planYear": 2026,
      "scoreGap": -20,
      "rankGap": 1979,
      "band": "稳妥",
      "track": "电子信息/通信/集成电路",
      "recommendation": "高优先",
      "expertScore": 92,
      "sourceLevel": "B",
      "admissionCategory": "普通类",
      "isCoverageAudit": false,
      "notes": "2025陕西物理普通批；和孩子工科接受度匹配，是640段重点补充项。",
      "planMatchType": "2025候选基线",
      "matched2025Major": "工科试验班（电气信息类）",
      "riskTags": [
        "大类分流/专业清待核"
      ],
      "priorityGroups": [
        "中坚九校"
      ],
      "focusOrder": 99,
      "action": "作为985好专业横向比较项，防止只盯重点校漏掉强专业。"
    },
    {
      "schoolKey": "tju",
      "school": "天津大学",
      "shortName": "天大",
      "city": "天津",
      "tier": "985/双一流",
      "major": "工科试验班（精仪与光电信息类）",
      "minScore": 641,
      "maxScore": 0,
      "avgScore": 0,
      "rank": 3671,
      "plan": 0,
      "planYear": 2026,
      "scoreGap": -21,
      "rankGap": 2113,
      "band": "稳妥",
      "track": "电子信息/通信/集成电路",
      "recommendation": "高优先",
      "expertScore": 90,
      "sourceLevel": "B",
      "admissionCategory": "普通类",
      "isCoverageAudit": false,
      "notes": "2025陕西物理普通批；不招色盲色弱，体检限制需核。",
      "planMatchType": "2025候选基线",
      "matched2025Major": "工科试验班（精仪与光电信息类）",
      "riskTags": [
        "大类分流/专业清待核",
        "近视度数不宜就读待核"
      ],
      "priorityGroups": [
        "中坚九校"
      ],
      "focusOrder": 99,
      "action": "作为985好专业横向比较项，防止只盯重点校漏掉强专业。"
    },
    {
      "schoolKey": "scut",
      "school": "华南理工大学",
      "shortName": "华工",
      "city": "广州",
      "tier": "985/双一流",
      "major": "工科试验班（AI与低空技术）",
      "minScore": 641,
      "maxScore": 0,
      "avgScore": 0,
      "rank": 3671,
      "plan": 0,
      "planYear": 2026,
      "scoreGap": -21,
      "rankGap": 2113,
      "band": "稳妥",
      "track": "低空/航空航天/无人系统",
      "recommendation": "高优先",
      "expertScore": 87,
      "sourceLevel": "B",
      "admissionCategory": "普通类",
      "isCoverageAudit": false,
      "notes": "2025陕西物理普通批；名称很契合，但需查课程和学院归属，避免只追热词。",
      "planMatchType": "2025候选基线",
      "matched2025Major": "工科试验班（AI与低空技术）",
      "riskTags": [
        "大类分流/专业清待核"
      ],
      "priorityGroups": [
        "中坚九校"
      ],
      "focusOrder": 99,
      "action": "作为985好专业横向比较项，防止只盯重点校漏掉强专业。"
    },
    {
      "schoolKey": "xmu",
      "school": "厦门大学",
      "shortName": "厦大",
      "city": "厦门",
      "tier": "985/双一流",
      "major": "电子信息类",
      "minScore": 640,
      "maxScore": 0,
      "avgScore": 0,
      "rank": 3788,
      "plan": 0,
      "planYear": 2026,
      "scoreGap": -22,
      "rankGap": 2230,
      "band": "稳妥",
      "track": "电子信息/通信/集成电路",
      "recommendation": "高优先",
      "expertScore": 92,
      "sourceLevel": "B",
      "admissionCategory": "普通类",
      "isCoverageAudit": false,
      "notes": "2025陕西物理普通批；翔安校区，集成电路后两年学分收费需复核。",
      "planMatchType": "2025候选基线",
      "matched2025Major": "电子信息类",
      "riskTags": [
        "大类分流/专业清待核"
      ],
      "priorityGroups": [
        "中坚九校"
      ],
      "focusOrder": 99,
      "action": "作为985好专业横向比较项，防止只盯重点校漏掉强专业。"
    },
    {
      "schoolKey": "scut",
      "school": "华南理工大学",
      "shortName": "华工",
      "city": "广州",
      "tier": "985/双一流",
      "major": "计算机类",
      "minScore": 639,
      "maxScore": 0,
      "avgScore": 0,
      "rank": 3888,
      "plan": 0,
      "planYear": 2026,
      "scoreGap": -23,
      "rankGap": 2330,
      "band": "稳妥",
      "track": "计算机/软件/AI/数据/网安",
      "recommendation": "高优先",
      "expertScore": 96,
      "sourceLevel": "B",
      "admissionCategory": "普通类",
      "isCoverageAudit": false,
      "notes": "2025陕西物理普通批；强985+计算机，属于重大遗漏补充。",
      "planMatchType": "2025候选基线",
      "matched2025Major": "计算机类",
      "riskTags": [
        "大类分流/专业清待核"
      ],
      "priorityGroups": [
        "中坚九校"
      ],
      "focusOrder": 99,
      "action": "作为985好专业横向比较项，防止只盯重点校漏掉强专业。"
    },
    {
      "schoolKey": "xmu",
      "school": "厦门大学",
      "shortName": "厦大",
      "city": "厦门",
      "tier": "985/双一流",
      "major": "计算机类",
      "minScore": 639,
      "maxScore": 0,
      "avgScore": 0,
      "rank": 3888,
      "plan": 0,
      "planYear": 2026,
      "scoreGap": -23,
      "rankGap": 2330,
      "band": "稳妥",
      "track": "计算机/软件/AI/数据/网安",
      "recommendation": "高优先",
      "expertScore": 93,
      "sourceLevel": "B",
      "admissionCategory": "普通类",
      "isCoverageAudit": false,
      "notes": "2025陕西物理普通批；翔安校区，软件工程后两年学分收费需复核。",
      "planMatchType": "2025候选基线",
      "matched2025Major": "计算机类",
      "riskTags": [
        "大类分流/专业清待核"
      ],
      "priorityGroups": [
        "中坚九校"
      ],
      "focusOrder": 99,
      "action": "作为985好专业横向比较项，防止只盯重点校漏掉强专业。"
    },
    {
      "schoolKey": "sdu",
      "school": "山东大学",
      "shortName": "山大",
      "city": "济南/青岛/威海",
      "tier": "985/双一流",
      "major": "计算机类",
      "minScore": 638,
      "maxScore": 0,
      "avgScore": 0,
      "rank": 0,
      "plan": 0,
      "planYear": 2026,
      "scoreGap": -24,
      "rankGap": -1558,
      "band": "稳妥",
      "track": "计算机/软件/AI/数据/网安",
      "recommendation": "高优先",
      "expertScore": 92,
      "sourceLevel": "B",
      "admissionCategory": "普通类",
      "isCoverageAudit": false,
      "notes": "愿意训练编程，未来AI时代需要系统能力和工程基本功。",
      "planMatchType": "2025候选基线",
      "matched2025Major": "计算机类",
      "riskTags": [
        "大类分流/专业清待核"
      ],
      "priorityGroups": [
        "985重点"
      ],
      "focusOrder": 99,
      "action": "作为985好专业横向比较项，防止只盯重点校漏掉强专业。"
    },
    {
      "schoolKey": "tju",
      "school": "天津大学",
      "shortName": "天大",
      "city": "天津",
      "tier": "985/双一流",
      "major": "工科试验班（智能制造与建造）",
      "minScore": 638,
      "maxScore": 0,
      "avgScore": 0,
      "rank": 4018,
      "plan": 0,
      "planYear": 2026,
      "scoreGap": -24,
      "rankGap": 2460,
      "band": "稳妥",
      "track": "自动化/机器人/智能制造/测控",
      "recommendation": "高优先",
      "expertScore": 88,
      "sourceLevel": "B",
      "admissionCategory": "普通类",
      "isCoverageAudit": false,
      "notes": "2025陕西物理普通批；含土木水利相关方向，需确认大类分流底线。",
      "planMatchType": "2025候选基线",
      "matched2025Major": "工科试验班（智能制造与建造）",
      "riskTags": [
        "大类分流/专业清待核"
      ],
      "priorityGroups": [
        "中坚九校"
      ],
      "focusOrder": 99,
      "action": "作为985好专业横向比较项，防止只盯重点校漏掉强专业。"
    },
    {
      "schoolKey": "scut",
      "school": "华南理工大学",
      "shortName": "华工",
      "city": "广州",
      "tier": "985/双一流",
      "major": "自动化/电气类/信息工程",
      "minScore": 637,
      "maxScore": 0,
      "avgScore": 0,
      "rank": 4146,
      "plan": 0,
      "planYear": 2026,
      "scoreGap": -25,
      "rankGap": 2588,
      "band": "985下探",
      "track": "电子信息/通信/集成电路",
      "recommendation": "高优先",
      "expertScore": 95,
      "sourceLevel": "B",
      "admissionCategory": "普通类",
      "isCoverageAudit": false,
      "notes": "2025陕西物理普通批多个方向同为637，可作为640下探时高质量985稳保。",
      "planMatchType": "2025候选基线",
      "matched2025Major": "自动化/电气类/信息工程",
      "riskTags": [
        "大类分流/专业清待核"
      ],
      "priorityGroups": [
        "中坚九校"
      ],
      "focusOrder": 99,
      "action": "作为985好专业横向比较项，防止只盯重点校漏掉强专业。"
    },
    {
      "schoolKey": "scu",
      "school": "四川大学",
      "shortName": "川大",
      "city": "成都",
      "tier": "985/双一流",
      "major": "电子信息类",
      "minScore": 637,
      "maxScore": 0,
      "avgScore": 0,
      "rank": 0,
      "plan": 0,
      "planYear": 2026,
      "scoreGap": -25,
      "rankGap": -1558,
      "band": "985下探",
      "track": "电子信息/通信/集成电路",
      "recommendation": "高优先",
      "expertScore": 95,
      "sourceLevel": "B",
      "admissionCategory": "普通类",
      "isCoverageAudit": false,
      "notes": "接受电路信号控制，且西电、成电、北邮、西工大等平台强。",
      "planMatchType": "2025候选基线",
      "matched2025Major": "电子信息类",
      "riskTags": [
        "大类分流/专业清待核"
      ],
      "priorityGroups": [
        "中坚九校"
      ],
      "focusOrder": 99,
      "action": "作为985好专业横向比较项，防止只盯重点校漏掉强专业。"
    },
    {
      "schoolKey": "xmu",
      "school": "厦门大学",
      "shortName": "厦大",
      "city": "厦门",
      "tier": "985/双一流",
      "major": "工科试验班（航空航天）",
      "minScore": 637,
      "maxScore": 0,
      "avgScore": 0,
      "rank": 4146,
      "plan": 0,
      "planYear": 2026,
      "scoreGap": -25,
      "rankGap": 2588,
      "band": "985下探",
      "track": "自动化/机器人/智能制造/测控",
      "recommendation": "高优先",
      "expertScore": 88,
      "sourceLevel": "B",
      "admissionCategory": "普通类",
      "isCoverageAudit": false,
      "notes": "2025陕西物理普通批；含机械、测控、自动化、飞行器方向，需查分流规则。",
      "planMatchType": "2025候选基线",
      "matched2025Major": "工科试验班（航空航天）",
      "riskTags": [
        "大类分流/专业清待核",
        "近视度数不宜就读待核"
      ],
      "priorityGroups": [
        "中坚九校"
      ],
      "focusOrder": 99,
      "action": "作为985好专业横向比较项，防止只盯重点校漏掉强专业。"
    },
    {
      "schoolKey": "hnu",
      "school": "湖南大学",
      "shortName": "湖大",
      "city": "长沙",
      "tier": "985/双一流",
      "major": "计算机科学与技术",
      "minScore": 631,
      "maxScore": 0,
      "avgScore": 0,
      "rank": 0,
      "plan": 0,
      "planYear": 2026,
      "scoreGap": -31,
      "rankGap": -1558,
      "band": "985下探",
      "track": "计算机/软件/AI/数据/网安",
      "recommendation": "高优先",
      "expertScore": 95,
      "sourceLevel": "B",
      "admissionCategory": "普通类",
      "isCoverageAudit": false,
      "notes": "愿意训练编程，未来AI时代需要系统能力和工程基本功。",
      "planMatchType": "2025候选基线",
      "matched2025Major": "计算机科学与技术",
      "riskTags": [],
      "priorityGroups": [
        "985重点"
      ],
      "focusOrder": 99,
      "action": "作为985好专业横向比较项，防止只盯重点校漏掉强专业。"
    },
    {
      "schoolKey": "csu",
      "school": "中南大学",
      "shortName": "中南",
      "city": "长沙",
      "tier": "985/双一流",
      "major": "软件工程",
      "minScore": 630,
      "maxScore": 0,
      "avgScore": 0,
      "rank": 0,
      "plan": 0,
      "planYear": 2026,
      "scoreGap": -32,
      "rankGap": -1558,
      "band": "985下探",
      "track": "计算机/软件/AI/数据/网安",
      "recommendation": "高优先",
      "expertScore": 95,
      "sourceLevel": "B",
      "admissionCategory": "普通类",
      "isCoverageAudit": false,
      "notes": "愿意训练编程，未来AI时代需要系统能力和工程基本功。",
      "planMatchType": "2025候选基线",
      "matched2025Major": "软件工程",
      "riskTags": [],
      "priorityGroups": [
        "985重点"
      ],
      "focusOrder": 99,
      "action": "作为985好专业横向比较项，防止只盯重点校漏掉强专业。"
    },
    {
      "schoolKey": "uestc",
      "school": "电子科技大学",
      "shortName": "成电",
      "city": "成都",
      "tier": "985/双一流",
      "major": "经济管理试验班（管理与电子工程双学位培养）",
      "minScore": null,
      "avgScore": null,
      "maxScore": null,
      "rank": null,
      "maxRank": null,
      "plan": 5,
      "planYear": 2026,
      "scoreGap": null,
      "rankGap": null,
      "band": "2025待核",
      "track": "电子信息/通信/集成电路/电气",
      "recommendation": "待核",
      "expertScore": 0,
      "sourceLevel": "A",
      "admissionCategory": "普通类",
      "isCoverageAudit": false,
      "notes": "2026计划专业；2025未找到同名或足够近似的普通类专业录取数据，需向招生办确认参考口径。",
      "planMatchType": "2025无同名或近似专业",
      "matched2025Major": "",
      "riskTags": [
        "2025无匹配"
      ],
      "priorityGroups": [
        "985重点"
      ],
      "focusOrder": 99
    }
  ]
}
